fake_snap/__init__.py
fake_snap/card.py
fake_snap/deck.py
fake_snap/game.py
fake_snap/location.py
fake_snap/main.py
fake_snap-0.1.1.dist-info/entry_points.txt
fake_snap-0.1.1.dist-info/LICENSE
fake_snap-0.1.1.dist-info/WHEEL
fake_snap-0.1.1.dist-info/METADATA
fake_snap-0.1.1.dist-info/RECORD
