Metadata-Version: 2.1
Name: fake_snap
Version: 0.1.1
Summary: This is the fake snap package. Created because multiplayer was not yet released.
Author-email: Joey Wheeler <joewheeler2048@gmail.com>, Noah Wheeler <tagordi@gmail.com>
Requires-Python: >=3.8
Project-URL: Home, https://git.jharmison.com/JediJoey/fake_snap
